dolphin/__init__.py
dolphin/__main__.py
dolphin/_decorators.py
dolphin/_log.py
dolphin/_overviews.py
dolphin/_show_versions.py
dolphin/_types.py
dolphin/_version.py
dolphin/baseline.py
dolphin/cli.py
dolphin/constants.py
dolphin/filtering.py
dolphin/goldstein.py
dolphin/interferogram.py
dolphin/interpolation.py
dolphin/log-config.json
dolphin/masking.py
dolphin/ps.py
dolphin/py.typed
dolphin/similarity.py
dolphin/stack.py
dolphin/stitching.py
dolphin/timeseries.py
dolphin/utils.py
dolphin/atmosphere/__init__.py
dolphin/atmosphere/ionosphere.py
dolphin/io/__init__.py
dolphin/io/_background.py
dolphin/io/_blocks.py
dolphin/io/_core.py
dolphin/io/_paths.py
dolphin/io/_process.py
dolphin/io/_readers.py
dolphin/io/_utils.py
dolphin/io/_writers.py
dolphin/phase_link/__init__.py
dolphin/phase_link/_closure_phase.py
dolphin/phase_link/_compress.py
dolphin/phase_link/_core.py
dolphin/phase_link/_eigenvalues.py
dolphin/phase_link/_ps_filling.py
dolphin/phase_link/covariance.py
dolphin/phase_link/crlb.py
dolphin/phase_link/metrics.py
dolphin/phase_link/simulate.py
dolphin/shp/__init__.py
dolphin/shp/_common.py
dolphin/shp/_glrt.py
dolphin/shp/_ks.py
dolphin/unwrap/__init__.py
dolphin/unwrap/_constants.py
dolphin/unwrap/_post_process.py
dolphin/unwrap/_snaphu_py.py
dolphin/unwrap/_tophu.py
dolphin/unwrap/_unwrap.py
dolphin/unwrap/_unwrap_3d.py
dolphin/unwrap/_utils.py
dolphin/unwrap/_whirlwind.py
dolphin/workflows/__init__.py
dolphin/workflows/_cli_config.py
dolphin/workflows/_utils.py
dolphin/workflows/corrections.py
dolphin/workflows/displacement.py
dolphin/workflows/ps.py
dolphin/workflows/sequential.py
dolphin/workflows/single.py
dolphin/workflows/stitching_bursts.py
dolphin/workflows/unwrapping.py
dolphin/workflows/wrapped_phase.py
dolphin/workflows/config/__init__.py
dolphin/workflows/config/_common.py
dolphin/workflows/config/_displacement.py
dolphin/workflows/config/_enums.py
dolphin/workflows/config/_ps.py
dolphin/workflows/config/_unwrap_options.py
dolphin-0.42.3.dist-info/licenses/LICENSE
dolphin-0.42.3.dist-info/METADATA
dolphin-0.42.3.dist-info/WHEEL
dolphin-0.42.3.dist-info/entry_points.txt
dolphin-0.42.3.dist-info/top_level.txt
dolphin-0.42.3.dist-info/RECORD
