Metadata-Version: 2.4
Name: dolphin
Version: 0.42.3
Summary: Workflows for generating surface displacement maps using InSAR
Project-URL: Homepage, https://github.com/isce-framework/dolphin
Project-URL: Bug Tracker, https://github.com/isce-framework/dolphin/issues
Classifier: Development Status :: 2 - Pre-Alpha
Classifier: Intended Audience :: Science/Research
Classifier: Programming Language :: Python :: 3
Classifier: Programming Language :: Python :: 3.10
Classifier: Programming Language :: Python :: 3.11
Classifier: Programming Language :: Python :: 3.12
Classifier: Programming Language :: Python :: 3.13
Classifier: Operating System :: OS Independent
Requires-Python: >=3.10
License-File: LICENSE
Requires-Dist: h5py>=3.6
Requires-Dist: jax>=0.4.19
Requires-Dist: numba>=0.56
Requires-Dist: numpy>=1.23
Requires-Dist: opera-utils>=0.4.1
Requires-Dist: pydantic>=2.1
Requires-Dist: pyproj>=3.3
Requires-Dist: rasterio>=1.3
Requires-Dist: ruamel_yaml>=0.15
Requires-Dist: scipy>=1.9
Requires-Dist: snaphu>=0.4.1
Requires-Dist: threadpoolctl>=3.0
Requires-Dist: tqdm>=4.60
Requires-Dist: tyro>=0.9.20
Provides-Extra: docs
Requires-Dist: markdown; extra == "docs"
Requires-Dist: mkdocs; extra == "docs"
Requires-Dist: mkdocs-gen-files; extra == "docs"
Requires-Dist: mkdocs-jupyter==0.25.0; extra == "docs"
Requires-Dist: mkdocs-literate-nav; extra == "docs"
Requires-Dist: mkdocs-material; extra == "docs"
Requires-Dist: mkdocs-section-index; extra == "docs"
Requires-Dist: mkdocstrings[python]; extra == "docs"
Requires-Dist: pybtex; extra == "docs"
Requires-Dist: pymdown-extensions; extra == "docs"
Provides-Extra: test
Requires-Dist: asv; extra == "test"
Requires-Dist: black; extra == "test"
Requires-Dist: boto3; extra == "test"
Requires-Dist: moto[s3,server]; extra == "test"
Requires-Dist: pooch; extra == "test"
Requires-Dist: pre-commit; extra == "test"
Requires-Dist: pytest; extra == "test"
Requires-Dist: pytest-cov; extra == "test"
Requires-Dist: pytest-randomly; extra == "test"
Requires-Dist: pytest-xdist; extra == "test"
Requires-Dist: shapely; extra == "test"
Requires-Dist: snaphu>=0.4.1; extra == "test"
Requires-Dist: xarray; extra == "test"
Dynamic: license-file
